oai_tools/__init__.py
oai_tools/cligpt.py
oai_tools/cligpt_completion.py
oai_tools-0.1.3.dist-info/LICENSE
oai_tools-0.1.3.dist-info/METADATA
oai_tools-0.1.3.dist-info/WHEEL
oai_tools-0.1.3.dist-info/entry_points.txt
oai_tools-0.1.3.dist-info/top_level.txt
oai_tools-0.1.3.dist-info/RECORD
