Metadata-Version: 2.1
Name: oai-tools
Version: 0.1.3
Summary: Collection of useful tools built on top of OpenAI's API
Home-page: https://github.com/filipgrano/oai_tools/tree/main
Author: Filip Granö
Author-email: filip-accounts@grano.me
License: UNKNOWN
Platform: UNKNOWN
Classifier: Development Status :: 3 - Alpha
Classifier: Intended Audience :: Developers
Classifier: License :: OSI Approved :: BSD License
Classifier: Programming Language :: Python :: 3
Classifier: Programming Language :: Python :: 3.7
Classifier: Programming Language :: Python :: 3.8
Classifier: Programming Language :: Python :: 3.9
Classifier: Programming Language :: Python :: 3.10
Classifier: Programming Language :: Python :: 3.11
Requires-Python: >=3.7
Requires-Dist: openai (>=0.27.0)
Requires-Dist: PyYAML
Requires-Dist: types-PyYAML
